michaelPanThematicLib/__init__.py
michaelPanThematicLib/draw_thematic_map_pillow.py
michaelPanThematicLib/test_thematic.py
michaelPanThematicLib/static/Helvetica-Neue-2.ttf
michaelPanThematicLib/static/global_-180_180.png
michaelPanThematicLib-1.0.2.dist-info/LICENSE
michaelPanThematicLib-1.0.2.dist-info/METADATA
michaelPanThematicLib-1.0.2.dist-info/WHEEL
michaelPanThematicLib-1.0.2.dist-info/top_level.txt
michaelPanThematicLib-1.0.2.dist-info/RECORD
