Metadata-Version: 2.1
Name: michaelPanThematicLib
Version: 1.0.2
Summary: draw thematic map.  Copyright (c) 2023 shinetek. All Rights Reserved
Author: chuntong pan
Author-email: panzhang1314@gmail.com
Platform: all
Classifier: Programming Language :: Python :: 3
Classifier: Operating System :: OS Independent
Requires-Python: >=3.8
License-File: LICENSE
Requires-Dist: pillow
Requires-Dist: michaelPanPrintLib
Requires-Dist: numpy
Requires-Dist: pydantic
